adash/__init__.py
adash/collection_util.py
adash/date_util.py
adash/file_util.py
adash/proportion.py
adash/string_util.py
adash-1.5.1.dist-info/METADATA
adash-1.5.1.dist-info/WHEEL
adash-1.5.1.dist-info/licenses/LICENSE
adash-1.5.1.dist-info/RECORD
