Metadata-Version: 2.1
Name: adash
Version: 1.5.1
Summary: Utility
Author-email: atu4403 <73111778+atu4403@users.noreply.github.com>
License-Expression: MIT
License-File: LICENSE
Classifier: License :: OSI Approved :: MIT License
Classifier: Programming Language :: Python :: 3
Classifier: Programming Language :: Python :: 3.8
Requires-Python: >=3.8
